{
  "website": "cos.com",
  "HOME_DELIVERY": {
    "available": "yes",
    "providers": [
      "not specified"
    ],
    "pricing": "150 Kč",
    "free_delivery_limit": "3500 Kč",
    "delivery_time": "3-5 working days",
    "express_delivery": {
      "available": "yes",
      "delivery_time": "1-2 working days",
      "pricing": "350 Kč"
    },
    "weekend_delivery": {
      "available": "no",
      "days": "not available"
    },
    "island_surcharge": "not available",
    "cod_surcharge": "not available"
  },
  "BULKY_PRODUCT_HOME_DELIVERY": {
    "available": "no",
    "providers": [],
    "pricing": "not available",
    "free_delivery_limit": "not available",
    "delivery_time": "not available",
    "express_delivery": {
      "available": "not available",
      "delivery_time": "not available",
      "pricing": "not available"
    },
    "weekend_delivery": {
      "available": "no",
      "days": "not available"
    },
    "island_surcharge": "not available",
    "cod_surcharge": "not available"
  },
  "PARCEL_SHOPS": {
    "available": "no",
    "providers": [],
    "locations_count": "not available",
    "pricing": "not available",
    "free_delivery_limit": "not available",
    "express_delivery": {
      "available": "not available",
      "delivery_time": "not available",
      "pricing": "not available"
    },
    "weekend_delivery": {
      "available": "no",
      "days": "not available"
    },
    "island_surcharge": "not available",
    "cod_surcharge": "not available"
  },
  "PARCEL_LOCKERS": {
    "available": "no",
    "providers": [],
    "locations_count": "not available",
    "pricing": "not available",
    "free_delivery_limit": "not available",
    "express_delivery": {
      "available": "not available",
      "delivery_time": "not available",
      "pricing": "not available"
    },
    "weekend_delivery": {
      "available": "no",
      "days": "not available"
    },
    "island_surcharge": "not available",
    "cod_surcharge": "not available"
  },
  "IN_STORE_PICKUP": {
    "available": "yes",
    "locations": [
      "Prague"
    ],
    "pricing": "Free",
    "free_delivery_limit": "not available",
    "express_delivery": {
      "available": "no",
      "delivery_time": "not available",
      "pricing": "not available"
    },
    "weekend_delivery": {
      "available": "no",
      "days": "not available"
    },
    "island_surcharge": "not available",
    "cod_surcharge": "not available"
  },
  "SUMMARY": "SUMMARY: COS offers standard and express home delivery, alongside free in-store pickup for customers in Czechia. Standard delivery costs 150 Kč (free on orders over 3500 Kč) and takes 3-5 working days. Express delivery is 350 Kč for a 1-2 day delivery time. Free Click & Collect is available at the Prague store. The store does not offer delivery to third-party parcel shops or lockers, nor is there a cash-on-delivery option.\nNOTABLE FEATURES: Key services include express delivery and free in-store pickup. Major limitations for the Czech market are the lack of parcel shop/locker options (e.g., Zásilkovna) and the absence of COD payments. The specific courier company is not disclosed.\nWEBSITE ASSESSMENT: Shipping information is easy to find and clearly stated in the Customer Service section. The details are sufficient for basic orders but lack information on the delivery partner and popular local delivery methods, which could be a drawback for some customers."
}